butty/__init__.py
butty/compat.py
butty/document.py
butty/engine.py
butty/errors.py
butty/fields.py
butty/py.typed
butty/query.py
butty/utility/__init__.py
butty/utility/oid_document.py
butty/utility/serialid_document.py
butty-1.0.1.dist-info/LICENSE
butty-1.0.1.dist-info/METADATA
butty-1.0.1.dist-info/WHEEL
butty-1.0.1.dist-info/RECORD
