Metadata-Version: 2.1
Name: butty
Version: 1.0.1
Summary: Lightweight fully typed ODM (Object-Document Mapper) for MongoDB
Home-page: https://github.com/AntonOvsyannikov/Butty
License: MIT
Author: aovsyannikov
Author-email: anton.ovsyannikov@gmail.com
Requires-Python: >=3.10,<4.0
Classifier: License :: OSI Approved :: MIT License
Classifier: Programming Language :: Python :: 3
Classifier: Programming Language :: Python :: 3.10
Classifier: Programming Language :: Python :: 3.11
Classifier: Programming Language :: Python :: 3.12
Requires-Dist: motor (>=3.7.1,<4.0.0)
Requires-Dist: pydantic (<3)
Requires-Dist: typing-inspect (>=0.9.0,<0.10.0)
Project-URL: Documentation, https://butty.readthedocs.io/
Project-URL: Repository, https://github.com/AntonOvsyannikov/Butty
